.hgignore
CHANGES.txt
CONTRIBUTORS.txt
MANIFEST.in
README.txt
TODO
setup.cfg
setup.py
docs/INSTALL.txt
docs/LICENSE.GPL
docs/LICENSE.txt
plumi/__init__.py
plumi.app.egg-info/PKG-INFO
plumi.app.egg-info/SOURCES.txt
plumi.app.egg-info/dependency_links.txt
plumi.app.egg-info/entry_points.txt
plumi.app.egg-info/namespace_packages.txt
plumi.app.egg-info/not-zip-safe
plumi.app.egg-info/requires.txt
plumi.app.egg-info/top_level.txt
plumi/app/__init__.py
plumi/app/adapters.py
plumi/app/config.py
plumi/app/configure.zcml
plumi/app/install.py
plumi/app/member_area.py
plumi/app/translations.py
plumi/app/version.txt
plumi/app/vocabs.py
plumi/app/Extensions/Install.py
plumi/app/Extensions/__init__.py
plumi/app/policy/__init__.py
plumi/app/policy/catalog_extension.py
plumi/app/policy/configure.zcml
plumi/app/policy/tests.py
plumi/app/policy/version.txt
plumi/app/profiles/default/actions.xml
plumi/app/profiles/default/catalog.xml
plumi/app/profiles/default/contentratings.xml
plumi/app/profiles/default/contenttyperegistry.xml
plumi/app/profiles/default/kupu.xml
plumi/app/profiles/default/mailhost.xml
plumi/app/profiles/default/memberdata_properties.xml
plumi/app/profiles/default/metadata.xml
plumi/app/profiles/default/portal_atct.xml
plumi/app/profiles/default/portal_languages.xml
plumi/app/profiles/default/portlets.xml
plumi/app/profiles/default/properties.xml
plumi/app/profiles/default/propertiestool.xml
plumi/app/profiles/default/rolemap.xml
plumi/app/profiles/default/skins.xml
plumi/app/profiles/default/viewlets.xml
plumi/app/profiles/default/workflows.xml
plumi/app/profiles/default/structure/.objects
plumi/app/profiles/default/structure/.properties
plumi/app/profiles/default/structure/default_member_content/.objects
plumi/app/profiles/default/structure/default_member_content/.properties
plumi/app/profiles/default/structure/default_member_content/callouts/.objects
plumi/app/profiles/default/structure/default_member_content/callouts/.properties
plumi/app/profiles/default/structure/default_member_content/events/.objects
plumi/app/profiles/default/structure/default_member_content/events/.properties
plumi/app/profiles/default/structure/default_member_content/news/.objects
plumi/app/profiles/default/structure/default_member_content/news/.properties
