Metadata-Version: 1.0
Name: plumi.app
Version: 0.11
Summary: Plumi application setup
Home-page: https://svn.plone.org/svn/collective/plumi.app/trunk
Author: Andy Nicholson
Author-email: andy@infiniterecursion.com.au
License: GPL
Keywords: plone plumi policy
Platform: UNKNOWN
Classifier: Framework :: Plone
Classifier: Programming Language :: Python
Classifier: Topic :: Software Development :: Libraries :: Python Modules
